{"stats":{"minecraft:dropped":{"minecraft:netherite_sword":5,"minecraft:raw_iron":5},"minecraft:custom":{"minecraft:time_since_rest":25796,"minecraft:sprint_one_cm":54846,"minecraft:damage_taken":1472,"minecraft:walk_one_cm":229559,"minecraft:damage_blocked_by_shield":400,"minecraft:mob_kills":17,"minecraft:drop":6,"minecraft:damage_dealt":1985,"minecraft:swim_one_cm":1264,"minecraft:fly_one_cm":331932,"minecraft:crouch_one_cm":6775,"minecraft:play_time":77206,"minecraft:deaths":4,"minecraft:sneak_time":1788,"minecraft:walk_under_water_one_cm":11544,"minecraft:jump":334,"minecraft:leave_game":9,"minecraft:walk_on_water_one_cm":21129,"minecraft:time_since_death":25776,"minecraft:climb_one_cm":644,"minecraft:total_world_time":77206,"minecraft:damage_resisted":4,"minecraft:fall_one_cm":4408},"minecraft:killed_by":{"minecraft:vindicator":1,"minecraft:creeper":1,"minecraft:spider":1},"minecraft:mined":{"minecraft:tall_seagrass":1,"minecraft:iron_ore":5,"minecraft:grass":7,"minecraft:grass_block":6,"minecraft:dirt":3,"minecraft:birch_wall_sign":5,"minecraft:copper_ore":5,"minecraft:stone":1,"minecraft:diorite":1,"minecraft:fern":1},"minecraft:used":{"minecraft:netherite_sword":51,"minecraft:trident":12,"minecraft:diorite":1,"minecraft:flint_and_steel":1,"minecraft:shield":15,"minecraft:spruce_sapling":88,"minecraft:totem_of_undying":1,"minecraft:rotten_flesh":5,"minecraft:cobblestone":1,"minecraft:dirt":9,"minecraft:mutton":2,"minecraft:porkchop":3,"minecraft:netherite_pickaxe":12,"minecraft:crossbow":4,"minecraft:bone_meal":70},"minecraft:picked_up":{"minecraft:raw_iron":10,"minecraft:porkchop":3,"minecraft:sand":18,"minecraft:spruce_sapling":2,"minecraft:ink_sac":5,"minecraft:diorite":1,"minecraft:string":2,"minecraft:dirt":9,"minecraft:raw_copper":15,"minecraft:bone":1,"minecraft:rotten_flesh":11,"minecraft:wheat_seeds":1,"minecraft:netherite_sword":6,"minecraft:birch_sign":4,"minecraft:mutton":2,"minecraft:white_wool":1,"minecraft:cobblestone":27},"minecraft:killed":{"minecraft:sheep":1,"minecraft:skeleton":2,"minecraft:zombie":5,"minecraft:pig":1,"minecraft:chicken":1,"minecraft:vindicator":2,"minecraft:spider":1,"minecraft:squid":3,"minecraft:cow":1}},"DataVersion":3105}